q_mem_mcp/__init__.py
q_mem_mcp/llm_summarizer.py
q_mem_mcp/memory_manager.py
q_mem_mcp/q_cli_sync.py
q_mem_mcp/server.py
q_mem_mcp_server-2.2.4.dist-info/METADATA
q_mem_mcp_server-2.2.4.dist-info/WHEEL
q_mem_mcp_server-2.2.4.dist-info/entry_points.txt
q_mem_mcp_server-2.2.4.dist-info/licenses/LICENSE
q_mem_mcp_server-2.2.4.dist-info/RECORD
