Metadata-Version: 2.4
Name: q-mem-mcp-server
Version: 2.2.4
Summary: Conversation memory and workspace management MCP server for Amazon Q CLI with SQLite + FTS5 storage and real-time sync
Project-URL: Homepage, https://github.com/jikjeong/q-mem-mcp-server
Project-URL: Repository, https://github.com/jikjeong/q-mem-mcp-server
Project-URL: Documentation, https://github.com/jikjeong/q-mem-mcp-server/blob/main/README.md
Project-URL: Issues, https://github.com/jikjeong/q-mem-mcp-server/issues
Author-email: jikjeong <jikjeong@amazon.com>
License: MIT
License-File: LICENSE
Keywords: amazon-q,conversation-memory,fts5,mcp,real-time-sync,sqlite,workspace-management
Classifier: Development Status :: 5 - Production/Stable
Classifier: Intended Audience :: Developers
Classifier: License :: OSI Approved :: MIT License
Classifier: Programming Language :: Python :: 3
Classifier: Programming Language :: Python :: 3.8
Classifier: Programming Language :: Python :: 3.9
Classifier: Programming Language :: Python :: 3.10
Classifier: Programming Language :: Python :: 3.11
Classifier: Programming Language :: Python :: 3.12
Classifier: Topic :: Database :: Database Engines/Servers
Classifier: Topic :: Software Development :: Libraries :: Python Modules
Classifier: Topic :: Text Processing :: Indexing
Requires-Python: >=3.8
Requires-Dist: mcp>=1.0.0
Requires-Dist: pydantic>=2.0.0
Requires-Dist: typing-extensions>=4.0.0
Provides-Extra: dev
Requires-Dist: black>=23.0.0; extra == 'dev'
Requires-Dist: isort>=5.12.0; extra == 'dev'
Requires-Dist: mypy>=1.0.0; extra == 'dev'
Requires-Dist: pytest-asyncio>=0.21.0; extra == 'dev'
Requires-Dist: pytest>=7.0.0; extra == 'dev'
